LICENSE.txt
setup.cfg
setup.py
ilollekhelperlib/ilollekhelperlib.py
ilollekhelperlib.egg-info/PKG-INFO
ilollekhelperlib.egg-info/SOURCES.txt
ilollekhelperlib.egg-info/dependency_links.txt
ilollekhelperlib.egg-info/requires.txt
ilollekhelperlib.egg-info/top_level.txt